[{"id":10554,"ayehNo":270,"text":["وَمَا ","أَنْفَقْتُمْ "],"sureh":2,"section":0,"pageNo":46},{"id":10555,"ayehNo":270,"text":["مِنْ ","نَفَقَةٍ "],"sureh":2,"section":1,"pageNo":46},{"id":10556,"ayehNo":270,"text":["أَوْ ","نَذَرْتُمْ "],"sureh":2,"section":2,"pageNo":46},{"id":10557,"ayehNo":270,"text":["مِنْ ","نَذْرٍ "],"sureh":2,"section":3,"pageNo":46},{"id":10558,"ayehNo":270,"text":["فَإِنَّ ","اللَّهَ "],"sureh":2,"section":4,"pageNo":46},{"id":10559,"ayehNo":270,"text":["يَعْلَمُهُ ","ۗ "],"sureh":2,"section":5,"pageNo":46},{"id":10560,"ayehNo":270,"text":["وَمَا ","لِلظَّالِمِينَ "],"sureh":2,"section":6,"pageNo":46},{"id":10561,"ayehNo":270,"text":["مِنْ ","أَنْصَارٍ "],"sureh":2,"section":7,"pageNo":46},{"id":10562,"ayehNo":271,"text":["إِنْ ","تُبْدُوا ","الصَّدَقَاتِ "],"sureh":2,"section":0,"pageNo":46},{"id":10563,"ayehNo":271,"text":["فَنِعِمَّا ","هِيَ ","ۖ "],"sureh":2,"section":1,"pageNo":46},{"id":10564,"ayehNo":271,"text":["وَإِنْ ","تُخْفُوهَا "],"sureh":2,"section":2,"pageNo":46},{"id":10565,"ayehNo":271,"text":["وَتُؤْتُوهَا ","الْفُقَرَاءَ "],"sureh":2,"section":3,"pageNo":46},{"id":10566,"ayehNo":271,"text":["فَهُوَ ","خَيْرٌ "],"sureh":2,"section":4,"pageNo":46},{"id":10567,"ayehNo":271,"text":["لَكُمْ ","ۚ "],"sureh":2,"section":5,"pageNo":46},{"id":10568,"ayehNo":271,"text":["وَيُكَفِّرُ ","عَنْكُمْ "],"sureh":2,"section":6,"pageNo":46},{"id":10569,"ayehNo":271,"text":["مِنْ ","سَيِّئَاتِكُمْ ","ۗ "],"sureh":2,"section":7,"pageNo":46},{"id":10570,"ayehNo":271,"text":["وَاللَّهُ ","بِمَا "],"sureh":2,"section":8,"pageNo":46},{"id":10571,"ayehNo":271,"text":["تَعْمَلُونَ ","خَبِيرٌ "],"sureh":2,"section":9,"pageNo":46},{"id":10572,"ayehNo":272,"text":["لَيْسَ ","عَلَيْكَ "],"sureh":2,"section":0,"pageNo":46},{"id":10573,"ayehNo":272,"text":["هُدَاهُمْ "],"sureh":2,"section":1,"pageNo":46},{"id":10574,"ayehNo":272,"text":["وَلَٰكِنَّ ","اللَّهَ "],"sureh":2,"section":2,"pageNo":46},{"id":10575,"ayehNo":272,"text":["يَهْدِي "],"sureh":2,"section":3,"pageNo":46},{"id":10576,"ayehNo":272,"text":["مَنْ ","يَشَاءُ ","ۗ "],"sureh":2,"section":4,"pageNo":46},{"id":10577,"ayehNo":272,"text":["وَمَا ","تُنْفِقُوا "],"sureh":2,"section":5,"pageNo":46},{"id":10578,"ayehNo":272,"text":["مِنْ ","خَيْرٍ "],"sureh":2,"section":6,"pageNo":46},{"id":10579,"ayehNo":272,"text":["فَلِأَنْفُسِكُمْ ","ۚ "],"sureh":2,"section":7,"pageNo":46},{"id":10580,"ayehNo":272,"text":["وَمَا ","تُنْفِقُونَ "],"sureh":2,"section":8,"pageNo":46},{"id":10581,"ayehNo":272,"text":["إِلَّا ","ابْتِغَاءَ "],"sureh":2,"section":9,"pageNo":46},{"id":10582,"ayehNo":272,"text":["وَجْهِ ","اللَّهِ ","ۚ "],"sureh":2,"section":10,"pageNo":46},{"id":10583,"ayehNo":272,"text":["وَمَا ","تُنْفِقُوا "],"sureh":2,"section":11,"pageNo":46},{"id":10584,"ayehNo":272,"text":["مِنْ ","خَيْرٍ "],"sureh":2,"section":12,"pageNo":46},{"id":10585,"ayehNo":272,"text":["يُوَفَّ ","إِلَيْكُمْ "],"sureh":2,"section":13,"pageNo":46},{"id":10586,"ayehNo":272,"text":["وَأَنْتُمْ "],"sureh":2,"section":14,"pageNo":46},{"id":10587,"ayehNo":272,"text":["لَا ","تُظْلَمُونَ "],"sureh":2,"section":15,"pageNo":46},{"id":10588,"ayehNo":273,"text":["لِلْفُقَرَاءِ ","الَّذِينَ "],"sureh":2,"section":0,"pageNo":46},{"id":10589,"ayehNo":273,"text":["أُحْصِرُوا "],"sureh":2,"section":1,"pageNo":46},{"id":10590,"ayehNo":273,"text":["فِي ","سَبِيلِ ","اللَّهِ "],"sureh":2,"section":2,"pageNo":46},{"id":10591,"ayehNo":273,"text":["لَا ","يَسْتَطِيعُونَ "],"sureh":2,"section":3,"pageNo":46},{"id":10592,"ayehNo":273,"text":["ضَرْبًا "],"sureh":2,"section":4,"pageNo":46},{"id":10593,"ayehNo":273,"text":["فِي ","الْأَرْضِ "],"sureh":2,"section":5,"pageNo":46},{"id":10594,"ayehNo":273,"text":["يَحْسَبُهُمُ ","الْجَاهِلُ "],"sureh":2,"section":6,"pageNo":46},{"id":10595,"ayehNo":273,"text":["أَغْنِيَاءَ "],"sureh":2,"section":7,"pageNo":46},{"id":10596,"ayehNo":273,"text":["مِنَ ","التَّعَفُّفِ "],"sureh":2,"section":8,"pageNo":46},{"id":10597,"ayehNo":273,"text":["تَعْرِفُهُمْ "],"sureh":2,"section":9,"pageNo":46},{"id":10598,"ayehNo":273,"text":["بِسِيمَاهُمْ "],"sureh":2,"section":10,"pageNo":46},{"id":10599,"ayehNo":273,"text":["لَا ","يَسْأَلُونَ ","النَّاسَ "],"sureh":2,"section":11,"pageNo":46},{"id":10600,"ayehNo":273,"text":["إِلْحَافًا ","ۗ "],"sureh":2,"section":12,"pageNo":46},{"id":10601,"ayehNo":273,"text":["وَمَا ","تُنْفِقُوا "],"sureh":2,"section":13,"pageNo":46},{"id":10602,"ayehNo":273,"text":["مِنْ ","خَيْرٍ "],"sureh":2,"section":14,"pageNo":46},{"id":10603,"ayehNo":273,"text":["فَإِنَّ ","اللَّهَ "],"sureh":2,"section":15,"pageNo":46},{"id":10604,"ayehNo":273,"text":["بِهِ ","عَلِيمٌ "],"sureh":2,"section":16,"pageNo":46},{"id":10605,"ayehNo":274,"text":["الَّذِينَ ","يُنْفِقُونَ "],"sureh":2,"section":0,"pageNo":46},{"id":10606,"ayehNo":274,"text":["أَمْوَالَهُمْ "],"sureh":2,"section":1,"pageNo":46},{"id":10607,"ayehNo":274,"text":["بِاللَّيْلِ ","وَالنَّهَارِ "],"sureh":2,"section":2,"pageNo":46},{"id":10608,"ayehNo":274,"text":["سِرًّا ","وَعَلَانِيَةً "],"sureh":2,"section":3,"pageNo":46},{"id":10609,"ayehNo":274,"text":["فَلَهُمْ ","أَجْرُهُمْ "],"sureh":2,"section":4,"pageNo":46},{"id":10610,"ayehNo":274,"text":["عِنْدَ ","رَبِّهِمْ "],"sureh":2,"section":5,"pageNo":46},{"id":10611,"ayehNo":274,"text":["وَلَا ","خَوْفٌ ","عَلَيْهِمْ "],"sureh":2,"section":6,"pageNo":46},{"id":10612,"ayehNo":274,"text":["وَلَا ","هُمْ ","يَحْزَنُونَ "],"sureh":2,"section":7,"pageNo":46}]